{
    "title": "Last Video of Hashtag Franco!!",
    "description": "Last Video of Hashtag Franco!! Help Subscribe to Pinoy top Loveteams here: https:\/\/goo.gl\/VoMjwD Follow us on Twitter: https:\/\/twitter.com\/Kathniel0969 Check ...",
    "referenceId": "7RU6Cmgzrxs",
    "date_created": "1510571910",
    "date_modified": "1510711452",
    "tags": "",
    "sourceId": null,
    "VIDEO_LENGTH": "SHORT",
    "status": "publishing",
    "visibility": "1",
    "VV_VI": null,
    "CVV_VI": null,
    "engagement_score": null,
    "conversion_score": null,
    "user_id": null,
    "id": "129592585",
    "loginId": "1758823",
    "entityType": "1",
    "titleTextEncoded": "Last-Video-of-Hashtag-Franco",
    "category": "",
    "duration": 125,
    "settings": "",
    "asset": {
        "type": "youtube",
        "thumbnailUrl": "https:\/\/i.ytimg.com\/vi\/7RU6Cmgzrxs\/hqdefault.jpg",
        "uploadDate": 1510571910,
        "videoId": "7RU6Cmgzrxs",
        "title": "Last Video of Hashtag Franco!!",
        "description": "Last Video of Hashtag Franco!! Help Subscribe to Pinoy top Loveteams here: https:\/\/goo.gl\/VoMjwD Follow us on Twitter: https:\/\/twitter.com\/Kathniel0969 Check ...",
        "author": "Pinoy Top Loveteams",
        "mediaDuration": 125,
        "prettyDuration": "00:02:05",
        "views": "12404"
    },
    "transcripts": "",
    "metrics_statistics": "",
    "tvp_profiles": [
        "14",
        "9"
    ],
    "tvp_profiles_manual": "",
    "tvp_profiles_maxscore": 208.5141
}